Week1/Day1/codes/good_mux.v

module good_mux (
    input i0,
    input i1,
    input sel,
    output reg y
);
  always @(*) begin
    if (sel) y <= i1;
    else y <= i0;
  end
endmodule

Week1/Day1/codes/tb_good_mux.v
`timescale 1ns / 1ps
module tb_good_mux;
  // Inputs
  reg i0, i1, sel;
  // Outputs
  wire y;

  // Instantiate the Unit Under Test (UUT)
  good_mux uut (
      .sel(sel),
      .i0 (i0),
      .i1 (i1),
      .y  (y)
  );

  initial begin
    $dumpfile("tb_good_mux.vcd");
    $dumpvars(0, tb_good_mux);
    // Initialize Inputs
    sel = 0;
    i0  = 0;
    i1  = 0;
    #300 $finish;
  end

  always #75 sel = ~sel;
  always #10 i0 = ~i0;
  always #55 i1 = ~i1;
endmodule

Week1/Day1/tb_good_mux.vcd
$date
	Wed Sep 24 22:06:20 2025
$end
$version
	Icarus Verilog
$end
$timescale
	1ps
$end
$scope module tb_good_mux $end
$var wire 1 ! y $end
$var reg 1 " i0 $end
$var reg 1 # i1 $end
$var reg 1 $ sel $end
$scope module uut $end
$var wire 1 " i0 $end
$var wire 1 # i1 $end
$var wire 1 $ sel $end
$var reg 1 ! y $end
$upscope $end
$upscope $end
$enddefinitions $end
$comment Show the parameter values. $end
$dumpall
$end
#0
$dumpvars
0$
0#
0"
0!
$end
#10000
1!
1"
#20000
0!
0"
#30000
1!
1"
#40000
0!
0"
#50000
1!
1"
#55000
1#
#60000
0!
0"
#70000
1!
1"
#75000
1$
#80000
0"
#90000
1"
#100000
0"
#110000
0!
1"
0#
#120000
0"
#130000
1"
#140000
0"
#150000
1!
1"
0$
#160000
0!
0"
#165000
1#
#170000
1!
1"
#180000
0!
0"
#190000
1!
1"
#200000
0!
0"
#210000
1!
1"
#220000
0!
0"
0#
#225000
1$
#230000
1"
#240000
0"
#250000
1"
#260000
0"
#270000
1"
#275000
1!
1#
#280000
0"
#290000
1"
#300000
0!
0"
0$
